remotefreebox
