Metadata-Version: 1.1
Name: remotefreebox
Version: 0.3
Summary: A Python module to control a Freebox v6 remotely
Home-page: https://github.com/MaximeCheramy/remotefreebox
Author: Maxime Chéramy and Francois Guibert
Author-email: maxime.cheramy@gmail.com
License: BSD
Keywords: freebox remote control rudp hid
Platform: UNKNOWN
Classifier: Development Status :: 4 - Beta
Classifier: Intended Audience :: Developers
Classifier: License :: OSI Approved :: BSD License
Classifier: Programming Language :: Python :: 3
Classifier: Programming Language :: Python :: 3.2
Classifier: Programming Language :: Python :: 3.3
Classifier: Programming Language :: Python :: 3.4
